{
  "generated_at": "2026-05-18",
  "quarter": "Q4",
  "quarter_window": "2026-03-26 to 2026-06-27",
  "focus_categories": [
    {
      "name": "Line Pipe",
      "category_id": 18,
      "tags": [
        "RIGID"
      ],
      "non_fta": {
        "utilization_pct": 73.92,
        "max_quota_kg": 2472000,
        "utilized_kg": 1827220,
        "remaining_kg": 644780,
        "max_country_share_pct": 59.0,
        "status": "Warning"
      },
      "fta": {
        "utilization_pct": 99.83,
        "max_quota_kg": 6248600,
        "utilized_kg": 6238019,
        "remaining_kg": 10581,
        "max_country_share_pct": 45.0,
        "status": "Critical"
      }
    },
    {
      "name": "Standard Pipe",
      "category_id": 20,
      "tags": [
        "EMT",
        "RIGID"
      ],
      "non_fta": {
        "utilization_pct": 99.27,
        "max_quota_kg": 10369200,
        "utilized_kg": 10293735,
        "remaining_kg": 75465,
        "max_country_share_pct": 21.0,
        "status": "Critical"
      },
      "fta": {
        "utilization_pct": 99.69,
        "max_quota_kg": 13489500,
        "utilized_kg": 13447888,
        "remaining_kg": 41612,
        "max_country_share_pct": 58.0,
        "status": "Critical"
      }
    }
  ],
  "source_urls": {
    "nfta": "https://www.eics-scei.gc.ca/report-rapport/TRQ_NFTA-Q4.csv",
    "fta": "https://www.eics-scei.gc.ca/report-rapport/TRQ_FTA-Q4.csv"
  },
  "notion_url": "https://www.notion.so/1aa5afdbe36a415fa32e9bf155625ca9"
}